LICENSE
MANIFEST.in
README.md
README.txt
setup.py
py_value_validator/__init__.py
py_value_validator/validation_functions.py
py_value_validator/value_validator.py
py_value_validator.egg-info/PKG-INFO
py_value_validator.egg-info/SOURCES.txt
py_value_validator.egg-info/dependency_links.txt
py_value_validator.egg-info/top_level.txt