Metadata-Version: 1.0
Name: py-value-validator
Version: 0.0.2
Summary: Value validation module
Home-page: http://pypi.python.org/pypi/py_value_validator/
Author: Andrew Seaman
Author-email: andrewseaman35@gmail.com
License: MIT
Platform: UNKNOWN
